README.md
setup.py
gkpt/__init__.py
gkpt/lib.py
gkpt.egg-info/PKG-INFO
gkpt.egg-info/SOURCES.txt
gkpt.egg-info/dependency_links.txt
gkpt.egg-info/requires.txt
gkpt.egg-info/top_level.txt