Metadata-Version: 1.0
Name: gkpt
Version: 1.0.0
Summary: Get ranking for your website in Google search for a particular keyword.
Home-page: https://github.com/serpsbotapi/gkpt
Author: SerpsBot
Author-email: sales@serpsbot.com
License: MIT
Platform: UNKNOWN
